numo_cli/__init__.py
numo_cli/__main__.py
numo_cli/main.py
numo_cli-0.2.2.dist-info/LICENSE
numo_cli-0.2.2.dist-info/METADATA
numo_cli-0.2.2.dist-info/WHEEL
numo_cli-0.2.2.dist-info/entry_points.txt
numo_cli-0.2.2.dist-info/top_level.txt
numo_cli-0.2.2.dist-info/RECORD
