Metadata-Version: 2.1
Name: numo-cli
Version: 0.2.2
Summary: A powerful CLI tool for calculations, unit conversions, and translations using Numo
Home-page: https://github.com/furkancosgun/numo-cli
Author: Furkan Cosgun
Author-email: furkan51cosgun@gmail.com
License: UNKNOWN
Project-URL: Bug Tracker, https://github.com/furkancosgun/numo-cli/issues
Project-URL: Documentation, https://github.com/furkancosgun/numo-cli#readme
Project-URL: Source Code, https://github.com/furkancosgun/numo-cli
Keywords: cli,calculator,converter,translator,utility,numo
Platform: UNKNOWN
Classifier: Development Status :: 3 - Alpha
Classifier: Environment :: Console
Classifier: Intended Audience :: End Users/Desktop
Classifier: Programming Language :: Python :: 3
Classifier: Programming Language :: Python :: 3.7
Classifier: Programming Language :: Python :: 3.8
Classifier: Programming Language :: Python :: 3.9
Classifier: Programming Language :: Python :: 3.10
Classifier: License :: OSI Approved :: MIT License
Classifier: Operating System :: OS Independent
Classifier: Topic :: Utilities
Requires-Python: >=3.7
License-File: LICENSE
Requires-Dist: numo>=0.2.4
